kamis/__init__.py
kamis/client.py
kamis/models/__init__.py
kamis/models/common.py
kamis/models/daily_sales_list.py
kamis/models/period_product_list.py
kamispy-0.1.3.dist-info/LICENSE
kamispy-0.1.3.dist-info/METADATA
kamispy-0.1.3.dist-info/WHEEL
kamispy-0.1.3.dist-info/top_level.txt
kamispy-0.1.3.dist-info/RECORD
