Metadata-Version: 2.1
Name: kamispy
Version: 0.1.3
Summary: KAMIS Open-API 비공식 파이썬 클라이언트
Home-page: https://github.com/spoqa/kamispy
Author: Spoqa Creators
Author-email: dev@spoqa.com
License: MIT License
Keywords: kamis,python-api
Platform: UNKNOWN
Classifier: Development Status :: 3 - Alpha
Classifier: License :: OSI Approved :: MIT License
Classifier: Programming Language :: Python :: 3 :: Only
Classifier: Programming Language :: Python :: 3.7
Classifier: Programming Language :: Python :: 3.8
Classifier: Programming Language :: Python :: 3.9
Classifier: Intended Audience :: Developers
Classifier: Topic :: Software Development
Classifier: Topic :: Software Development :: Libraries :: Python Modules
Classifier: Topic :: Utilities
Requires-Python: >=3.7.0
Requires-Dist: requests
Provides-Extra: tests
Requires-Dist: flake8 ; extra == 'tests'
Requires-Dist: pytest ; extra == 'tests'
Requires-Dist: requests-mock ; extra == 'tests'
